[
  {
    "Date": "11/05/2025",
    "EmployeeID": "2602069620",
    "ClockIn": "00:15:00",
    "ClockOut": "00:30:00",
    "DailyLog": "aaa"
  },
  {
    "Date": "11/05/2025",
    "EmployeeID": "2602099863",
    "ClockIn": "00:15:00",
    "ClockOut": "00:30:00",
    "DailyLog": "aaa"
  },
  {
    "Date": "11/05/2025",
    "EmployeeID": "2702326744",
    "ClockIn": "00:15:00",
    "ClockOut": "00:30:00",
    "DailyLog": "aaa"
  },
  {
    "Date": "11/05/2025",
    "EmployeeID": "2702258535",
    "ClockIn": "00:15:00",
    "ClockOut": "00:30:00",
    "DailyLog": "aaa"
  },
  {
    "Date": "12/05/2025",
    "EmployeeID": "2702258535",
    "ClockIn": "00:15:00",
    "ClockOut": "00:30:00",
    "DailyLog": "aaa"
  },
  {
    "Date": "12/05/2025",
    "EmployeeID": "2602076336",
    "ClockIn": "00:15:00",
    "ClockOut": "00:30:00",
    "DailyLog": "aaa"
  }
]